openimis_be_policyholder-1.9.0.dist-info/licenses/LICENSE.md
policyholder/__init__.py
policyholder/admin.py
policyholder/apps.py
policyholder/models.py
policyholder/schema.py
policyholder/services.py
policyholder/signals.py
policyholder/urls.py
policyholder/views.py
policyholder/gql/__init__.py
policyholder/gql/gql_types.py
policyholder/gql/gql_mutations/__init__.py
policyholder/gql/gql_mutations/create_mutations.py
policyholder/gql/gql_mutations/delete_mutations.py
policyholder/gql/gql_mutations/input_types.py
policyholder/gql/gql_mutations/replace_mutation.py
policyholder/gql/gql_mutations/update_mutations.py
policyholder/management/__init__.py
policyholder/management/commands/__init__.py
policyholder/management/commands/generatepolicyholders.py
policyholder/migrations/0001_initial.py
policyholder/migrations/0002_auto_20201214_1237.py
policyholder/migrations/0003_auto_20201214_1239.py
policyholder/migrations/0004_auto_20201214_1302.py
policyholder/migrations/0005_auto_20210111_1254.py
policyholder/migrations/0006_policyholdercontributionplanmutation_policyholderinsureemutation_policyholdermutation_policyholderus.py
policyholder/migrations/0007_auto_20210118_0927.py
policyholder/migrations/0008_auto_20210118_1109.py
policyholder/migrations/0009_auto_20210118_1127.py
policyholder/migrations/0010_auto_20210126_1040.py
policyholder/migrations/0011_auto_20210408_0937.py
policyholder/migrations/0012_auto_20210408_0949.py
policyholder/migrations/0013_auto_20210408_0951.py
policyholder/migrations/0014_auto_20210408_1007.py
policyholder/migrations/0015_auto_20210624_1243.py
policyholder/migrations/0016_policyholder_roles_for_admin.py
policyholder/migrations/0017_auto_20230126_0903.py
policyholder/migrations/0018_alter_historicalpolicyholder_date_created_and_more.py
policyholder/migrations/__init__.py
policyholder/tests/__init__.py
policyholder/tests/helpers.py
policyholder/tests/helpers_tests.py
policyholder/tests/services/__init__.py
policyholder/tests/services/services_ph_tests.py
policyholder/validation/__init__.py
openimis_be_policyholder-1.9.0.dist-info/METADATA
openimis_be_policyholder-1.9.0.dist-info/WHEEL
openimis_be_policyholder-1.9.0.dist-info/top_level.txt
openimis_be_policyholder-1.9.0.dist-info/RECORD
